lennpy/__init__.py
lennpy/command_line.py
lennpy/faces.py
lennpy-0.0.8.dist-info/LICENSE
lennpy-0.0.8.dist-info/METADATA
lennpy-0.0.8.dist-info/WHEEL
lennpy-0.0.8.dist-info/entry_points.txt
lennpy-0.0.8.dist-info/top_level.txt
lennpy-0.0.8.dist-info/RECORD
