Metadata-Version: 2.1
Name: lennpy
Version: 0.0.8
Summary: Generate Lenny Faces
Home-page: https://github.com/Histefanhere/lennpy
Author: Stefan Zdravkovic
Author-email: stefan.zdra@gmail.com
License: GNU GPLv3
Keywords: lenny,memes
Platform: UNKNOWN
Classifier: Development Status :: 3 - Alpha
Classifier: Programming Language :: Python :: 3
Classifier: Programming Language :: Python :: 3.6
Classifier: Programming Language :: Python :: 3.7
Classifier: Programming Language :: Python :: 3.8
Classifier: License :: OSI Approved :: GNU General Public License v3 (GPLv3)
Classifier: Operating System :: OS Independent
